tea/__init__.py
tea/errors.py
tea/logger.py
tea/serde.py
tea/timestamp.py
tea/version.py
tea/ctx/__init__.py
tea/decorators/__init__.py
tea/dsa/__init__.py
tea/dsa/config.py
tea/dsa/plugin.py
tea/dsa/singleton.py
tea/msg/__init__.py
tea/msg/mail.py
tea/process/__init__.py
tea/process/process.py
tea/process/wrappers.py
tea/shell/__init__.py
tea/shell/__main__.py
tea/tests/__init__.py
tea/tests/test_ctx.py
tea/tests/test_decorators.py
tea/tests/test_logger.py
tea/tests/test_process.py
tea/tests/test_serde.py
tea/tests/test_shell.py
tea/tests/test_utils.py
tea/tests/test_version.py
tea/tests/dsa/__init__.py
tea/tests/dsa/test_config.py
tea/tests/dsa/test_multiconfig.py
tea/tests/dsa/test_singleton.py
tea/utils/__init__.py
tea/utils/encoding.py
tea/utils/html.py
tea-0.1.7.dist-info/AUTHORS
tea-0.1.7.dist-info/LICENSE
tea-0.1.7.dist-info/METADATA
tea-0.1.7.dist-info/WHEEL
tea-0.1.7.dist-info/top_level.txt
tea-0.1.7.dist-info/RECORD
