Metadata-Version: 2.1
Name: tea
Version: 0.1.7
Summary: Set of utility python modules.
Home-page: https://github.com/alefnula/tea
Author: Viktor Kerkez
Author-email: alefnula@gmail.com
Maintainer: Viktor Kerkez
Maintainer-email: alefnula@gmail.com
License: Apache-2.0
Platform: Windows
Platform: POSIX
Platform: MacOSX
Classifier: Programming Language :: Python :: 3
Classifier: Programming Language :: Python :: 3.7
Classifier: Programming Language :: Python :: 3.8
Classifier: License :: OSI Approved :: Apache Software License
Classifier: Operating System :: OS Independent
License-File: LICENSE
License-File: AUTHORS
